ffx/__init__.py
ffx/api.py
ffx/cli.py
ffx/time_utils.py
ffx/core/__init__.py
ffx/core/approach.py
ffx/core/bases.py
ffx/core/build_strategy.py
ffx/core/constants.py
ffx/core/model_factories.py
ffx/core/models.py
ffx/core/utils.py
ffx-2.1.0.dist-info/METADATA
ffx-2.1.0.dist-info/WHEEL
ffx-2.1.0.dist-info/entry_points.txt
ffx-2.1.0.dist-info/licenses/LICENSE
ffx-2.1.0.dist-info/RECORD
