Metadata-Version: 2.4
Name: ffx
Version: 2.1.0
Summary: Fast Function Extraction: A fast, scalable, and deterministic symbolic regression tool.
Project-URL: Homepage, https://github.com/natekupp/ffx
Project-URL: Repository, https://github.com/natekupp/ffx
Author-email: Trent McConaghy <gtrent@gmail.com>, Nate Kupp <nathan.kupp@gmail.com>
Maintainer-email: Nate Kupp <nathan.kupp@gmail.com>
License: FFX Software Licence Agreement (like BSD, but adapted for
License-File: LICENSE
Keywords: machine learning,symbolic regression
Classifier: Development Status :: 4 - Beta
Classifier: Environment :: Console
Classifier: Intended Audience :: Developers
Classifier: Programming Language :: Python
Classifier: Programming Language :: Python :: 3.9
Classifier: Programming Language :: Python :: 3.10
Classifier: Programming Language :: Python :: 3.11
Classifier: Programming Language :: Python :: 3.12
Classifier: Topic :: Scientific/Engineering
Requires-Python: >=3.9
Requires-Dist: click>=5.0
Requires-Dist: contextlib2>=0.5.4
Requires-Dist: numpy
Requires-Dist: pandas
Requires-Dist: scikit-learn
